paypal/__init__.py
paypal/utils.py
paypal/pro/__init__.py
paypal/pro/admin.py
paypal/pro/creditcard.py
paypal/pro/exceptions.py
paypal/pro/fields.py
paypal/pro/forms.py
paypal/pro/helpers.py
paypal/pro/models.py
paypal/pro/views.py
paypal/pro/migrations/0001_initial.py
paypal/pro/migrations/0002_auto_20141117_1647.py
paypal/pro/migrations/0003_auto_20181128_1032.py
paypal/pro/migrations/__init__.py
paypal/pro/templates/pro/confirm.html
paypal/pro/templates/pro/payment.html
paypal/pro/tests/__init__.py
paypal/pro/tests/settings.py
paypal/pro/tests/test_doDirectPayment_authenticated_user.yaml
paypal/pro/tests/test_doDirectPayment_invalid.yaml
paypal/pro/tests/test_doDirectPayment_valid.yaml
paypal/pro/tests/test_doDirectPayment_valid_with_signal.yaml
paypal/pro/tests/test_get_redirect.yaml
paypal/pro/tests/test_pro.py
paypal/pro/tests/test_setExpressCheckout.yaml
paypal/pro/tests/test_validate_confirm_form_error.yaml
paypal/pro/tests/templates/confirmation.html
paypal/pro/tests/templates/payment.html
paypal/standard/__init__.py
paypal/standard/conf.py
paypal/standard/forms.py
paypal/standard/helpers.py
paypal/standard/models.py
paypal/standard/widgets.py
paypal/standard/ipn/__init__.py
paypal/standard/ipn/admin.py
paypal/standard/ipn/forms.py
paypal/standard/ipn/models.py
paypal/standard/ipn/signals.py
paypal/standard/ipn/urls.py
paypal/standard/ipn/views.py
paypal/standard/ipn/migrations/0001_initial.py
paypal/standard/ipn/migrations/0002_paypalipn_mp_id.py
paypal/standard/ipn/migrations/0003_auto_20141117_1647.py
paypal/standard/ipn/migrations/0004_auto_20150612_1826.py
paypal/standard/ipn/migrations/0005_auto_20151217_0948.py
paypal/standard/ipn/migrations/0006_auto_20160108_1112.py
paypal/standard/ipn/migrations/0007_auto_20160219_1135.py
paypal/standard/ipn/migrations/0008_auto_20181128_1032.py
paypal/standard/ipn/migrations/__init__.py
paypal/standard/ipn/templates/ipn/ipn.html
paypal/standard/ipn/templates/ipn/ipn_test.html
django_paypal-2.1.dist-info/LICENSE
django_paypal-2.1.dist-info/METADATA
django_paypal-2.1.dist-info/WHEEL
django_paypal-2.1.dist-info/top_level.txt
django_paypal-2.1.dist-info/RECORD
